bact_archiver_bessyii/__init__.py
bact_archiver_bessyii/utils/__init__.py
bact_archiver_bessyii/utils/fofb_bpm_data.py
bact_archiver_bessyii-0.0.0.data/data/config/archiver.cfg
bact_archiver_bessyii-0.0.0.dist-info/LICENSE
bact_archiver_bessyii-0.0.0.dist-info/METADATA
bact_archiver_bessyii-0.0.0.dist-info/WHEEL
bact_archiver_bessyii-0.0.0.dist-info/top_level.txt
bact_archiver_bessyii-0.0.0.dist-info/RECORD
