Metadata-Version: 2.1
Name: bact-archiver-bessyii
Version: 0.0.0
Summary: EPICS archiver appliance access using google protobuf. Configuration for BESSY II
Home-page: https://github.com/hz-b/bact-archiver
Author: Andreas Schälicke, Pierre Schnizer
Author-email: andreas.schaelicke@helmholtz-berlin.de
